alpha_transform/AdaptiveAlpha.py
alpha_transform/AlphaTransformUtility.py
alpha_transform/MotherShearlets.py
alpha_transform/SphereTransform.py
alpha_transform/__init__.py
alpha_transform/fourier_util.py
alpha_transform-0.0.1.dist-info/LICENSE
alpha_transform-0.0.1.dist-info/METADATA
alpha_transform-0.0.1.dist-info/WHEEL
alpha_transform-0.0.1.dist-info/top_level.txt
alpha_transform-0.0.1.dist-info/RECORD
