Metadata-Version: 2.1
Name: alpha-transform
Version: 0.0.1
Summary: Adaptive alpha shearlet transform for manifold-valued data
Home-page: https://github.com/dedale-fet/alpha-transform
Author: Felix Voigtlaender
Author-email: felix@voigtlaender.xyz
License: MIT
Platform: UNKNOWN
Requires-Dist: numpy
Requires-Dist: matplotlib
Requires-Dist: numexpr
Requires-Dist: pyfftw
Requires-Dist: tqdm
Requires-Dist: healpy
Requires-Dist: Pillow
Requires-Dist: scipy
